{
  "date": "24/07/2026",
  "rashifal": [
    {
      "TITLE": "મેષ રાશિ - 'The Dynamic Pioneer' - 24/07/2026",
      "IMAGE": "mesh.jpg",
      "OUTPUT_FILENAME": "mesh-rashifal-24072026.mp4",
      "YOUTUBE_SHORT_TITLE": "મેષ રાશિ: શુક્રવારે વૈભવ અને પ્રગતિનો યોગ, ઉત્સાહથી બનશે દરેક કામ! 🚀🌸 #Mesh #Aries",
      "BG_MUSIC": "Corporate Motivational Rock",
      "RASHI_NAME": "MESH RASHI (મેષ રાશિ)",
      "content": {
        "આજનો વાઇબ (The Vibe)": "શુક્રવારનો દિવસ તમારામાં નવી તાજગી, ઉત્સાહ અને સુંદર કાર્યો તરફ આકર્ષણ લાવશે.",
        "કરિયર અને કામકાજ (Work/Hustle)": "ઓફિસ અને વ્યાપારમાં સહકર્મીઓનો ઉત્તમ સાથ મળશે. ક્રિએટિવ આઈડિયાઝથી બિઝનેસમાં મોટો ગ્રોથ જોવા મળશે.",
        "પૈસા અને ખિસ્સું (Wallet Talk)": "આર્થિક સ્થિતિ ખૂબ સંતુલિત અને મજબૂત રહેશે. સુખ-સુવિધાઓ અથવા શોપિંગ પાછળ શુભ ખર્ચ થઈ શકે છે.",
        "પ્રેમ અને સંબંધો (Heart Matters)": "દામ્પત્ય જીવનમાં રોમાન્સ અને મધુરતા વધશે. મિત્રો સાથે સાંજનો સમય અત્યંત આનંદદાયક વિતશે.",
        "સ્વાસ્થ્ય અને ફિટનેસ (Body & Soul)": "શારીરિક અને માનસિક તંદુરસ્તી ઉત્તમ રહેશે. વર્કઆઉટ અને યોગથી એનર્જી જાળવી રાખવી.",
        "દૈનિક ઉપાય (The Spiritual Hack)": "દેવી મહાલક્ષ્મીજી સમક્ષ દેશી ઘીનો દીવો પ્રગટાવી લાલ કે સફેદ ફૂલ અર્પણ કરો.",
        "PRO-TIP (Pro-Tip)": "તમારા પોઝિટિવ ઉત્સાહને સાચી દિશામાં લગાવો, ઉતાવળિયા નિર્ણયો લેવાનું ટાળવું."
      }
    },
    {
      "TITLE": "વૃષભ રાશિ - 'The Charming Builder' - 24/07/2026",
      "IMAGE": "vrushabh.jpg",
      "OUTPUT_FILENAME": "vrushabh-rashifal-24072026.mp4",
      "YOUTUBE_SHORT_TITLE": "વૃષભ રાશિ: તમારી જ રાશિના સ્વામી શુક્રદેવનો દિવસ, આર્થિક લાભ અને સુખની વર્ષા! 💰🌸 #Vrushabh #Taurus",
      "BG_MUSIC": "Calm Acoustic Business",
      "RASHI_NAME": "VRUSHABH RASHI (વૃષભ રાશિ)",
      "content": {
        "આજનો વાઇબ (The Vibe)": "તમારી રાશિના સ્વામી શુક્રદેવનો જ વાર હોવાથી આજે તમારામાં આકર્ષણ, સંતોષ અને માનસિક પ્રસન્નતા છવાયેલી રહેશે.",
        "કરિયર અને કામકાજ (Work/Hustle)": "કલા, ડિઝાઇનિંગ, ફેશન કે લક્ઝરી ક્ષેત્ર સાથે જોડાયેલા લોકોને મોટી સફળતા અને નવો આર્થિક કન્ટ્રેક્ટ મળશે.",
        "પૈસા અને ખિસ્સું (Wallet Talk)": "આકસ્મિક ધનલાભ થવાના પ્રબળ યોગ છે. ભૌતિક સુખ-સુવિધાઓ અને મિલકતમાં રોકાણ માટે શ્રેષ્ઠ દિવસ છે.",
        "પ્રેમ અને સંબંધો (Heart Matters)": "પ્રેમ સંબંધોમાં નવી તાજગી અને મીઠાશ અનુભવાશે. પાર્ટનર સાથે આહલાદક સમય વિતાવવાનો મોકો મળશે.",
        "સ્વાસ્થ્ય અને ફિટનેસ (Body & Soul)": "આરોગ્ય અને પર્સનાલિટી ચમકશે. સ્કીન કેલ્શિયમ કે હેલ્થ કેર માટે દિવસ ઉત્તમ છે.",
        "દૈનિક ઉપાય (The Spiritual Hack)": "મહાલક્ષ્મી અષ્ટકમનો પાઠ કરો અને ખીરનો પ્રસાદ અર્પણ કરો.",
        "PRO-TIP (Pro-Tip)": "આજના દિવસનો સદઉપયોગ કરીને તમારા અટકેલા મહત્વપૂર્ણ નિર્ણયો પૂર્ણ કરી લો."
      }
    },
    {
      "TITLE": "મિથુન રાશિ - 'The Versatile Communicator' - 24/07/2026",
      "IMAGE": "mithun.jpg",
      "OUTPUT_FILENAME": "mithun-rashifal-24072026.mp4",
      "YOUTUBE_SHORT_TITLE": "મિથુન રાશિ: શુક્રવારે નેટવર્કિંગ અને ક્રિએટિવિટીથી નફો, વ્યાપારમાં નવી તકો! 📊✨ #Mithun #Gemini",
      "BG_MUSIC": "Upbeat Modern Ambient",
      "RASHI_NAME": "MITHUN RASHI (મિથુન રાશિ)",
      "content": {
        "આજનો વાઇબ (The Vibe)": "વાણીની મધુરતા અને તાર્કિક વિચારસરણીથી લોકો તમારાથી પ્રભાવિત થશે. વાતાવરણ હળવુંફૂલ રહેશે.",
        "કરિયર અને કામકાજ (Work/Hustle)": "માર્કેટિંગ, મીડિયા, કન્ટેન્ટ અને પીઆરના ક્ષેત્રે મોટો લાભ થશે. ઓફિસમાં તમારી કામગીરીની પ્રશંસા થશે.",
        "પૈસા અને ખિસ્સું (Wallet Talk)": "નાણાકીય આવકમાં સુધારો થશે. મનોરંજન કે પ્રવાસ પાછળ બજેટ મુજબ ખર્ચ થઈ શકે છે.",
        "પ્રેમ અને સંબંધો (Heart Matters)": "મિત્રો સાથેની મુલાકાત નવી ઉર્જા આપશે. દામ્પત્ય જીવનમાં પરસ્પર અંડરસ્ટેન્ડિંગ સુધરશે.",
        "સ્વાસ્થ્ય અને ફિટનેસ (Body & Soul)": "માનસિક સ્ફૂર્તિ અદભુત રહેશે. પાણીનું પ્રમાણ પૂરતું રાખીને હાઇડ્રેટેડ રહેવું.",
        "દૈનિક ઉપાય (The Spiritual Hack)": "નાની કન્યાઓને મીઠાઈ અથવા સફેદ મિષ્ટાન અર્પણ કરો.",
        "PRO-TIP (Pro-Tip)": "તમારા વ્યાવસાયિક નેટવર્કનો યોગ્ય ઉપયોગ કરીને અટકેલા કામો આગળ ધપાવો."
      }
    },
    {
      "TITLE": "કર્ક રાશિ - 'The Caring Anchor' - 24/07/2026",
      "IMAGE": "kark.jpg",
      "OUTPUT_FILENAME": "kark-rashifal-24072026.mp4",
      "YOUTUBE_SHORT_TITLE": "કર્ક રાશિ: શુક્રવારે કૌટુંબિક સુખ અને શાંતિ, જૂની ચિંતાઓ થશે દૂર! 🌊💗 #Kark #Cancer",
      "BG_MUSIC": "Serene Peaceful Flow",
      "RASHI_NAME": "KARK RASHI (કર્ક રાશિ)",
      "content": {
        "આજનો વાઇબ (The Vibe)": "ભાવનાત્મક ગંભીરતા સાથે આંતરિક સંતોષ અને પારિવારિક સુખ-શાંતિ આજે મુખત્ત્વ મેળવશે.",
        "કરિયર અને કામકાજ (Work/Hustle)": "કાર્યસ્થળે વાતાવરણ સાનુકૂળ રહેશે. હોસ્પિટાલિટી કે રિયલ એસ્ટેટ સાથે જોડાયેલા લોકોને નફો મળશે.",
        "પૈસા અને ખિસ્સું (Wallet Talk)": "ઘરના સુશોભન કે વાહન પાછળ ખર્ચ થઈ શકે છે. આર્થિક પરિસ્થિતિ સ્થિર અને સુરક્ષિત રહેશે.",
        "પ્રેમ અને સંબંધો (Heart Matters)": "પરિવારજનો પ્રત્યે પ્રેમ અને સહાનુભૂતિ વધશે. જીવનસાથીનો પૂરતો સહયોગ ચિંતાઓ દૂર કરશે.",
        "સ્વાસ્થ્ય અને ફિટનેસ (Body & Soul)": "સ્વાસ્થ્ય સારું રહેશે. સાંજ સમયે મેડિટેશન કે હળવા સંગીતથી મન પ્રસન્ન રાખવું.",
        "દૈનિક ઉપાય (The Spiritual Hack)": "દેવી દુર્ગા અથવા લક્ષ્મીજીને ગુલાબનું ફૂલ ચડાવો.",
        "PRO-TIP (Pro-Tip)": "નકારાત્મક વિચારોથી દૂર રહીને પરિવાર સાથે ગુણવત્તાસભર સમય વિતાવો."
      }
    },
    {
      "TITLE": "સિંહ રાશિ - 'The Radiant Leader' - 24/07/2026",
      "IMAGE": "singh.jpg",
      "OUTPUT_FILENAME": "singh-rashifal-24072026.mp4",
      "YOUTUBE_SHORT_TITLE": "સિંહ રાશિ: શુક્રવારે તમારો પ્રભાવ અને ચમક વધશે, લીડરશીપમાં મોટી સફળતા! 🦁✨ #Singh #Leo",
      "BG_MUSIC": "Epic Regal Trumpets",
      "RASHI_NAME": "SINGH RASHI (સિંહ રાશિ)",
      "content": {
        "આજનો વાઇબ (The Vibe)": "તમારું આકર્ષણ, આત્મવિશ્વાસ અને ભવ્ય શૈલી આજના દિવસને રોયલ બનાવશે.",
        "કરિયર અને કામકાજ (Work/Hustle)": "બિઝનેસ અને મેનેજમેન્ટમાં નવી સિદ્ધિઓ પ્રાપ્ત થશે. પ્રેઝન્ટેશન કે મીટિંગ્સમાં તમારી વાણી છવાઈ જશે.",
        "પૈસા અને ખિસ્સું (Wallet Talk)": "આવકના નવા માર્ગો ખુલશે. કાયમી બચત તથા રોકાણમાં ઉત્સુકતા વધશે.",
        "પ્રેમ અને સંબંધો (Heart Matters)": "સામાજિક વર્તુળમાં તમારો આદર વધશે. લવ લાઈફમાં રોમાંચક ક્ષણો અનુભવાશે.",
        "સ્વાસ્થ્ય અને ફિટનેસ (Body & Soul)": "શારીરિક ઉર્જા ઉત્તમ રહેશે. દિનચર્યામાં પૌષ્ટિક આહારનો સમાવેશ કરવો.",
        "દૈનિક ઉપાય (The Spiritual Hack)": "મહાલક્ષ્મીજીના મંત્ર 'ૐ શ્રીં મહાલક્ષ્મ્યૈ નમઃ' નો ૧૦૮ વાર જાપ કરો.",
        "PRO-TIP (Pro-Tip)": "તમારી ઉદારતા જાળવી રાખો પરંતુ નિર્ણય લેતી વખતે વ્યવહારુ અભિગમ રાખવો."
      }
    },
    {
      "TITLE": "કન્યા રાશિ - 'The Elegant Organizer' - 24/07/2026",
      "IMAGE": "kanya.jpg",
      "OUTPUT_FILENAME": "kanya-rashifal-24072026.mp4",
      "YOUTUBE_SHORT_TITLE": "કન્યા રાશિ: શુક્રવારે આયોજનબદ્ધ કામથી મોટો ફાયદો, બજેટિંગ રહેશે સચોટ! 📊🌸 #Kanya #Virgo",
      "BG_MUSIC": "Smooth Corporate Grid",
      "RASHI_NAME": "KANYA RASHI (કન્યા રાશિ)",
      "content": {
        "આજનો વાઇબ (The Vibe)": "સચોટ કાર્યશૈલી અને સૌંદર્યલક્ષી આયોજનથી દરેક જટિલ કામ સરળ બની જશે.",
        "કરિયર અને કામકાજ (Work/Hustle)": "ઓફિસમાં અટકેલા હિસાબો અને ફાઇલો પૂર્ણ થશે. ટેકનિકલ કે વહીવટી કાર્યોમાં પ્રગતિ મળશે.",
        "પૈસા અને ખિસ્સું (Wallet Talk)": "નાણાકીય આયોજન સચોટ રહેશે. ખર્ચ ઉપર નિયંત્રણ રહેવાથી આર્થિક માનસિક શાંતિ મળશે.",
        "પ્રેમ અને સંબંધો (Heart Matters)": "સંબંધોમાં ગેરસમજો ઉકેલાશે. જીવનસાથી સાથે વિતાવેલો શાંત સમય હૂંફ આપશે.",
        "સ્વાસ્થ્ય અને ફિટનેસ (Body & Soul)": "આરોગ્ય ઉત્તમ રહેશે. ત્વચા અને આંખોની સંભાળ માટે પૂરતો આરામ અને પાણી જરૂરી છે.",
        "દૈનિક ઉપાય (The Spiritual Hack)": "તુલસીજીના છોડમાં જળ અર્પણ કરો અને દેશી ઘીનો દીવો કરો.",
        "PRO-TIP (Pro-Tip)": "અતિ વિશ્લેષણથી બચીને સહજતાથી દરેક પરિસ્થિતિનો સ્વીકાર કરો."
      }
    },
    {
      "TITLE": "તુલા રાશિ - 'The Ultimate Stylist' - 24/07/2026",
      "IMAGE": "tula.jpg",
      "OUTPUT_FILENAME": "tula-rashifal-24072026.mp4",
      "YOUTUBE_SHORT_TITLE": "તુલા રાશિ: તમારી રાશિના સ્વામી શુક્રદેવ! શુક્રવારે કલા, પ્રેમ અને વ્યાપારમાં ભવ્ય સફળતા! ⚖️💖 #Tula #Libra",
      "BG_MUSIC": "Elegant Light Corporate",
      "RASHI_NAME": "TULA RASHI (તુલા રાશિ)",
      "content": {
        "આજનો વાઇબ (The Vibe)": "તમારી રાશિના સ્વામી શુક્રદેવ હોવાથી આજના દિવસે સુંદરતા, સંતુલન અને આનંદ ઉત્સવ જેવો અનુભવ કરાવશે.",
        "કરિયર અને કામકાજ (Work/Hustle)": "કળા, ફેશન, આર્કિટેક્ચર કે ટ્રેડિંગના ક્ષેત્રે જબરદસ્ત લાભ થશે. નવી ભાગીદારી માટે શ્રેષ્ઠ તક છે.",
        "પૈસા અને ખિસ્સું (Wallet Talk)": "આર્થિક સ્થિતિ અત્યંત મજબૂત બનશે. અટકેલા પૈસા પાછા મળવાના મજબૂત યોગ બની રહ્યા છે.",
        "પ્રેમ અને સંબંધો (Heart Matters)": "પ્રેમ સંબંધો શિખરે રહેશે. જીવનસાથી સાથે કોઈ ખાસ ડાઇનિંગ કે રોમેન્ટિક સરપ્રાઇઝનો પ્લાન બનશે.",
        "સ્વાસ્થ્ય અને ફિટનેસ (Body & Soul)": "સ્વાસ્થ્ય ફિટ અને ફ્રેશ રહેશે. મનની પ્રસન્નતા તમારી પર્સનાલિટીને વધુ નિખારશે.",
        "દૈનિક ઉપાય (The Spiritual Hack)": "લક્ષ્મીજીને સફેદ મિષ્ટાન અથવા સાકર અર્પણ કરો અને પરફ્યુમ કે ઇત્તરનો ઉપયોગ કરો.",
        "PRO-TIP (Pro-Tip)": "આજના અત્યંત શુભ સમયનો પૂરતો લાભ લઈને કરિયર અને પર્સનલ લાઈફમાં આગળ વધો."
      }
    },
    {
      "TITLE": "વૃશ્ચિક રાશિ - 'The Passionate Strategist' - 24/07/2026",
      "IMAGE": "vrushchik.jpg",
      "OUTPUT_FILENAME": "vrushchik-rashifal-24072026.mp4",
      "YOUTUBE_SHORT_TITLE": "વૃશ્ચિક રાશિ: શુક્રવારે તમારી ગૂઢ ક્ષમતાથી બિઝનેસમાં મોટો ધનલાભ! 🦂🔥 #Vrushchik #Scorpio",
      "BG_MUSIC": "Deep Intense Cinematic",
      "RASHI_NAME": "VRUSHCHIK RASHI (વૃશ્ચિક રાશિ)",
      "content": {
        "આજનો વાઇબ (The Vibe)": "તમારી આંતરિક ઊંડાઈ, જુસ્સો અને પરિસ્થિતિઓ બદલવાની તાકાત આજે ચરમસીમાએ રહેશે.",
        "કરિયર અને કામકાજ (Work/Hustle)": "સંશોધન કે ઇનોવેટિવ પ્રોજેક્ટ્સમાં ધાર્યા કરતા મોટો નફો મળશે. હરીફો સામે તમારો વિજય થશે.",
        "પૈસા અને ખિસ્સું (Wallet Talk)": "આકસ્મિક નાણાકીય લાભ અને જૂના રોકાણોમાંથી ઉત્તમ વળતર મળવાના આશાસ્પદ સંકેતો છે.",
        "પ્રેમ અને સંબંધો (Heart Matters)": "સંબંધોમાં સચ્ચાઈ અને ઊંડી આત્મીયતા વધશે. પરિવાર સાથે મહત્વના મુદ્દાઓ ઉકેલાશે.",
        "સ્વાસ્થ્ય અને ફિટનેસ (Body & Soul)": "માનસિક એનર્જી હાઈ રહેશે. હળવી કસરત અને યોગથી શરીરમાં ફ્રેશનેસ જળવાશે.",
        "દૈનિક ઉપાય (The Spiritual Hack)": "દુર્ગા ચાલીસાના પાઠ કરો અને કન્યાઓને ફળ-પ્રસાદ અર્પણ કરો.",
        "PRO-TIP (Pro-Tip)": "તમારા વિઝનને સ્પષ્ટ રાખીને અટકેલા કાર્યોમાં ઝડપથી આગળ વધો."
      }
    },
    {
      "TITLE": "ધન રાશિ - 'The Generous Seeker' - 24/07/2026",
      "IMAGE": "dhanu.jpg",
      "OUTPUT_FILENAME": "dhanu-rashifal-23072026.mp4",
      "YOUTUBE_SHORT_TITLE": "ધન રાશિ: શુક્રવારે પ્રવાસ અને સામાજિક પ્રતિષ્ઠામાં વધારો, ધનલાભનો યોગ! 🎯✨ #Dhanu #Sagittarius",
      "BG_MUSIC": "Inspiring Cinematic Corporate",
      "RASHI_NAME": "DHANU RASHI (ધન રાશિ)",
      "content": {
        "આજનો વાઇબ (The Vibe)": "ઉદારતા, પોઝિટિવિટિ અને આનંદદાયક વાતાવરણ આજે તમારો દિવસ ઉત્સાહથી ભરી દેશે.",
        "કરિયર અને કામકાજ (Work/Hustle)": "શિક્ષણ, ટૂરિઝમ અને સલાહકાર ક્ષેત્રમાં સારો ગ્રોથ જોવા મળશે. નવી તકો હાથ લાગશે.",
        "પૈસા અને ખિસ્સું (Wallet Talk)": "આર્થિક બજેટ સંતુલિત રહેશે. ધાર્મિક કે મનોરંજન સંબંધિત કાર્યોમાં સુખદ ખર્ચ થશે.",
        "પ્રેમ અને સંબંધો (Heart Matters)": "પરિવારમાં ખુશી અને આનંદ છવાયેલો રહેશે. પ્રિયજન સાથે લાંબા પ્રવાસનું આયોજન થઈ શકે છે.",
        "સ્વાસ્થ્ય અને ફિટનેસ (Body & Soul)": "સ્વાસ્થ્ય એકંદરે ફિટ રહેશે. સવારની તાજી હવામાં વૉક કરવાથી માનસિક શાંતિ મળશે.",
        "દૈનિક ઉપાય (The Spiritual Hack)": "મહાલક્ષ્મીજીનું સ્મરણ કરીને ગાયને ગળ્યા દૂધમાંથી બનેલી વાની ખવડાવો.",
        "PRO-TIP (Pro-Tip)": "મળતી ખુશીઓને સહર્ષ સ્વીકારીને આશાવાદી વલણ જાળવી રાખવું."
      }
    },
    {
      "TITLE": "મકર રાશિ - 'The Disciplined Creator' - 24/07/2026",
      "IMAGE": "makar.jpg",
      "OUTPUT_FILENAME": "makar-rashifal-24072026.mp4",
      "YOUTUBE_SHORT_TITLE": "મકર રાશિ: શુક્રવારે ધૈર્ય અને પરિશ્રમથી કરિયરમાં વડીલોનો સહયોગ, મોટો નફો! 🏔️💼 #Makar #Capricorn",
      "BG_MUSIC": "Grounded Business Electro",
      "RASHI_NAME": "MAKAR RASHI (મકર રાશિ)",
      "content": {
        "આજનો વાઇબ (The Vibe)": "વ્યાવહારિક દ્રષ્ટિકોણ અને શિસ્તબદ્ધ શૈલીથી તમે દરેક કામમાં સફળતા હાસિલ કરશો.",
        "કરિયર અને કામકાજ (Work/Hustle)": "સ્થાવર મિલકત કે બાંધકામ સાથે જોડાયેલા કામોમાં ઝડપી ગતિ આવશે. નોકરીમાં પ્રમોશનના સંકેત મળે.",
        "પૈસા અને ખિસ્સું (Wallet Talk)": "આર્થિક ક્ષેત્રે મોટું સુરક્ષિત રોકાણ શક્ય બનશે. આવકમાં સ્થિરતા આવતા ચિંતા દૂર થશે.",
        "પ્રેમ અને સંબંધો (Heart Matters)": "પરિવાર પ્રત્યેની તમારી ફરજો પૂરી કરશો. દામ્પત્યમાં વિશ્વાસ અને સમજણ વધશે.",
        "સ્વાસ્થ્ય અને ફિટનેસ (Body & Soul)": "શારીરિક થાક ટાળવા માટે કામની વચ્ચે પૂરતો બ્રેક લેવો અને યોગ્ય આહાર લેવો.",
        "દૈનિક ઉપાય (The Spiritual Hack)": "દેવી મહાલક્ષ્મીજીની સામે ઘીનો દીવો કરીને કમળનું ફૂલ અર્પણ કરો.",
        "PRO-TIP (Pro-Tip)": "કામનો અતિશય બોજ ન લેતા પરિવાર માટે યોગ્ય સમય ફાળવવો."
      }
    },
    {
      "TITLE": "કુંભ રાશિ - 'The Innovative Visionary' - 24/07/2026",
      "IMAGE": "kumbh.jpg",
      "OUTPUT_FILENAME": "kumbh-rashifal-24072026.mp4",
      "YOUTUBE_SHORT_TITLE": "કુંભ રાશિ: શુક્રવારે ડિજિટલ નેટવર્કિંગથી નવો ગ્રોથ, મિત્રો તરફથી મોટી ભેટ! 💡🚀 #Kumbh #Aquarius",
      "BG_MUSIC": "Modern High-Tech Synth",
      "RASHI_NAME": "KUMBH RASHI (કુંભ રાશિ)",
      "content": {
        "આજનો વાઇબ (The Vibe)": "નવી વિચારસરણી, ટેકનોલોજી અને ક્રિએટિવ ઇનોવેશનથી આજનો દિવસ ખાસ બનશે.",
        "કરિયર અને કામકાજ (Work/Hustle)": "ઓનલાઈન વ્યાપાર, આઈટી અથવા ક્રિએટિવ ફિલ્ડમાં જોડાયેલા લોકોને ઉચ્ચ સફળતા મળશે.",
        "પૈસા અને ખિસ્સું (Wallet Talk)": "આર્થિક પરિસ્થિતિ અનુકૂળ રહેશે. ડિજિટલ પ્રોજેક્ટ્સ કે નવા કરારથી ફાયદો થશે.",
        "પ્રેમ અને સંબંધો (Heart Matters)": "મિત્રો તથા સામાજિક મિત્રવર્તુળ તરફથી ખુશીઓ મળશે. લવ લાઈફ ઉત્સાહજનક રહેશે.",
        "સ્વાસ્થ્ય અને ફિટનેસ (Body & Soul)": "માનસિક એનર્જી સારી રહેશે. આંખોના આરામ માટે ડિજિટલ સ્ક્રીનનો સમય મર્યાદિત રાખવો.",
        "દૈનિક ઉપાય (The Spiritual Hack)": "મહાલક્ષ્મીજીને કમળ અથવા ગુલાબ અર્પણ કરીને આરતી કરો.",
        "PRO-TIP (Pro-Tip)": "નવા ક્રિએટિવ આઈડિયાઝ પર કામ કરવાનું શરૂ કરી દો, ભવિષ્યમાં સુંદર પરિણામ મળશે."
      }
    },
    {
      "TITLE": "મીન રાશિ - 'The Ethereal Dreamer' - 24/07/2026",
      "IMAGE": "meen.jpg",
      "OUTPUT_FILENAME": "meen-rashifal-24072026.mp4",
      "YOUTUBE_SHORT_TITLE": "મીન રાશિ: શુક્રવારે કલાત્મકતા અને આધ્યાત્મિક પ્રસન્નતા, આકસ્મિક ધનલાભ! 🌊🌸 #Meen #Pisces",
      "BG_MUSIC": "Dreamy Ethereal Ambient",
      "RASHI_NAME": "MEEN RASHI (મીન રાશિ)",
      "content": {
        "આજનો વાઇબ (The Vibe)": "કલાત્મકતા, આંતરિક સંતોષ અને પવિત્ર વિચારોથી આજનો દિવસ અત્યંત શાંતિપૂર્ણ વિતશે.",
        "કરિયર અને કામકાજ (Work/Hustle)": "કાઉન્સિલિંગ, કલા કે કાલ્પનિક ક્ષેત્રના પ્રોજેક્ટ્સમાં પ્રગતિ થશે. વિદેશથી શુભ સમાચાર મળી શકે છે.",
        "પૈસા અને ખિસ્સું (Wallet Talk)": "નાણાકીય સ્થિતિમાં સુધારો થશે. જૂના રોકાણોમાંથી સુખદ આર્થિક લાભ મેળવવાના યોગ છે.",
        "પ્રેમ અને સંબંધો (Heart Matters)": "દામ્પત્ય જીવનમાં આત્મિક જોડાણ મહેસૂસ થશે. પરિવારજનો સાથે સંબંધો પવિત્ર અને મધુર બનશે.",
        "સ્વાસ્થ્ય અને ફિટનેસ (Body & Soul)": "માનસિક શાંતિ રહેશે. યોગાભ્યાસ અને ધ્યાન કરવાથી શારીરિક સ્ફૂર્તિ જળવાઈ રહેશે.",
        "દૈનિક ઉપાય (The Spiritual Hack)": "લક્ષ્મી સ્તોત્રનો પાઠ કરો અને ગરીબ કન્યાઓને દૂધ કે ખીર આપો.",
        "PRO-TIP (Pro-Tip)": "તમારા આંતરિક અવાજ (Intuition) પર વિશ્વાસ રાખીને મહત્વપૂર્ણ નિર્ણયો લો."
      }
    }
  ]
}
