{
  "date": "07/05/2026",
  "rashifal": [
    {
      "TITLE": "મેષ રાશિ - 'The Brave Messenger' - 07/05/2026",
      "IMAGE": "mesh.jpg",
      "OUTPUT_FILENAME": "mesh-rashifal-07052026.mp4",
      "YOUTUBE_SHORT_TITLE": "મેષ રાશિ: પરાક્રમમાં વધારો અને ભાઈ-બહેનોનો સાથ! 🚀 #Mesh #Thursday",
      "BG_MUSIC": "Fast & Rhythmic",
      "RASHI_NAME": "MESH RASHI (મેષ રાશિ)",
      "content": {
        "આજનો વાઇબ (The Vibe)": "ત્રીજા ભાવમાં ચંદ્ર હોવાથી તમારો આત્મવિશ્વાસ સાતમા આસમાને હશે. તમે કોઈપણ પડકાર ઝીલવા તૈયાર રહેશો.",
        "કરિયર અને કામકાજ (Work/Hustle)": "માર્કેટિંગ અને સેલ્સ સાથે જોડાયેલા લોકો માટે શ્રેષ્ઠ દિવસ. ટૂંકી મુસાફરીથી મોટો ફાયદો થઈ શકે છે. નવા આઈડિયાઝ અમલમાં મૂકશો.",
        "પૈસા અને ખિસ્સું (Wallet Talk)": "આર્થિક સ્થિતિમાં સુધારો થશે. નાના રોકાણથી સારું વળતર મળી શકે છે. ભાઈ-બહેનો તરફથી આર્થિક મદદ મળવાની શક્યતા.",
        "પ્રેમ અને સંબંધો (Heart Matters)": "સામાજિક વર્તુળ વધશે. જૂના મિત્રો સાથે મુલાકાત થશે. જીવનસાથી તમારા સાહસની પ્રશંસા કરશે.",
        "સ્વાસ્થ્ય અને ફિટનેસ (Body & Soul)": "તમે ખૂબ જ ઉર્જાવાન અનુભવશો. ખભા કે હાથમાં નાનો દુખાવો થઈ શકે છે, તેથી વધુ પડતો શ્રમ ટાળવો.",
        "દૈનિક ઉપાય (The Spiritual Hack)": "ભગવાન વિષ્ણુને પીળા ફૂલ અર્પણ કરો અને વિષ્ણુ સહસ્ત્રનામનો પાઠ કરો.",
        "પ્રો-ટીપ (Pro-Tip)": "આજે તમારી વાતચીત કરવાની કળાથી તમે અઘરા કામ પાર પાડી શકશો."
      }
    },
    {
      "TITLE": "વૃષભ રાશિ - 'The Financial Architect' - 07/05/2026",
      "IMAGE": "vrushabh.jpg",
      "OUTPUT_FILENAME": "vrushabh-rashifal-07052026.mp4",
      "YOUTUBE_SHORT_TITLE": "વૃષભ રાશિ: ધનલાભના યોગ અને પરિવારમાં ખુશીઓ! 💰 #Vrushabh #Wealth",
      "BG_MUSIC": "Elegant & Peaceful",
      "RASHI_NAME": "VRUSHABH RASHI (વૃષભ રાશિ)",
      "content": {
        "આજનો વાઇબ (The Vibe)": "બીજા ભાવમાં ચંદ્ર હોવાથી તમારું ધ્યાન બચત અને પારિવારિક મૂલ્યો પર રહેશે. તમારી વાણી પ્રભાવશાળી રહેશે.",
        "કરિયર અને કામકાજ (Work/Hustle)": "પૈતૃક વ્યવસાયમાં લાભ થશે. બૌદ્ધિક કાર્યોમાં તમારી પ્રશંસા થશે. ઓફિસમાં તમારી ગંભીરતા તમને સફળતા અપાવશે.",
        "પૈસા અને ખિસ્સું (Wallet Talk)": "આર્થિક રોકાણ માટે દિવસ અનુકૂળ છે. અટકેલા નાણાં પરત મળી શકે છે. ખર્ચ પર તમારો કાબૂ રહેશે.",
        "પ્રેમ અને સંબંધો (Heart Matters)": "પરિવારમાં કોઈ માંગલિક પ્રસંગની ચર્ચા થઈ શકે છે. જીવનસાથી સાથે મધુર સંબંધો રહેશે. સંબંધીઓ સાથે મુલાકાત થશે.",
        "સ્વાસ્થ્ય અને ફિટનેસ (Body & Soul)": "ખાનપાનમાં ધ્યાન રાખવું. ગળા કે મોઢાની નાની તકલીફ થઈ શકે છે. હળદળવાળું દૂધ લેવું ફાયદાકારક રહેશે.",
        "દૈનિક ઉપાય (The Spiritual Hack)": "કેળાના વૃક્ષની પૂજા કરો અને ગાયને ચણાની દાળ અને ગોળ ખવડાવો.",
        "પ્રો-ટીપ (Pro-Tip)": "આજે કરેલું આર્થિક આયોજન ભવિષ્યમાં મોટી સુરક્ષા આપશે."
      }
    },
    {
      "TITLE": "મિથુન રાશિ - 'The Versatile Communicator' - 07/05/2026",
      "IMAGE": "mithun.jpg",
      "OUTPUT_FILENAME": "mithun-rashifal-07052026.mp4",
      "YOUTUBE_SHORT_TITLE": "મિથુન રાશિ: ચંદ્ર તમારી રાશિમાં! આત્મવિશ્વાસ અને નવી તકોનો ઉદય! ✨ #Mithun #Shine",
      "BG_MUSIC": "Upbeat & Trendy",
      "RASHI_NAME": "MITHUN RASHI (મિથુન રાશિ)",
      "content": {
        "આજનો વાઇબ (The Vibe)": "ચંદ્ર તમારી જ રાશિમાં હોવાથી તમે માનસિક રીતે ખૂબ જ સક્રિય અને ખુશખુશાલ રહેશો. લોકો તમારા તરફ આકર્ષાશે.",
        "કરિયર અને કામકાજ (Work/Hustle)": "કરિયરમાં નવી શરૂઆત કરવા માટે શ્રેષ્ઠ દિવસ. તમારી નિર્ણય લેવાની ક્ષમતા તેજ બનશે. નોકરીમાં તમારી પર્સનાલિટીનો પ્રભાવ પડશે.",
        "પૈસા અને ખિસ્સું (Wallet Talk)": "આર્થિક સ્થિતિમાં સુધારો થશે. તમે તમારી જરૂરિયાતો પાછળ ખર્ચ કરશો. કોઈ નવી આવકનો સ્ત્રોત શરૂ થઈ શકે છે.",
        "પ્રેમ અને સંબંધો (Heart Matters)": "સિંગલ્સ માટે કોઈ નવી વ્યક્તિના આગમનના સંકેત છે. જીવનસાથી સાથેના સંબંધોમાં નવી તાજગી આવશે. સામાજિક માન-પ્રતિષ્ઠા વધશે.",
        "સ્વાસ્થ્ય અને ફિટનેસ (Body & Soul)": "સ્વાસ્થ્ય ઉત્તમ રહેશે. તમે શારીરિક રીતે સ્ફૂર્તિ અનુભવશો. સકારાત્મક વિચારોથી મન પ્રફુલ્લિત રહેશે.",
        "દૈનિક ઉપાય (The Spiritual Hack)": "મહાદેવ પર જળાભિષેક કરો અને પીળા ચંદનનું તિલક લગાવો.",
        "પ્રો-ટીપ (Pro-Tip)": "આજે તમારી આવડત બતાવવાની એક પણ તક જતી ન કરશો."
      }
    },
    {
      "TITLE": "કર્ક રાશિ - 'The Spiritual Voyager' - 07/05/2026",
      "IMAGE": "kark.jpg",
      "OUTPUT_FILENAME": "kark-rashifal-07052026.mp4",
      "YOUTUBE_SHORT_TITLE": "કર્ક રાશિ: ખર્ચ પર કાબૂ રાખવો અને વિદેશથી લાભના યોગ! 🌍 #Kark #Peace",
      "BG_MUSIC": "Calm & Ambient",
      "RASHI_NAME": "KARK RASHI (કર્ક રાશિ)",
      "content": {
        "આજનો વાઇબ (The Vibe)": "બારમા ભાવમાં ચંદ્ર હોવાથી મન થોડું વિચારોમાં અટવાયેલું રહેશે. આધ્યાત્મિકતા તરફ ઝુકાવ વધશે.",
        "કરિયર અને કામકાજ (Work/Hustle)": "કામમાં થોડો વિલંબ થઈ શકે છે. વિદેશી કંપનીઓ સાથે જોડાયેલા લોકોને ફાયદો થશે. ઓફિસમાં શાંત રહીને કામ પૂર્ણ કરવું.",
        "પૈસા અને ખિસ્સું (Wallet Talk)": "અણધાર્યા ખર્ચની શક્યતા છે. બજેટ મુજબ ચાલવું હિતાવહ છે. દાન-પુણ્યમાં ખર્ચ થઈ શકે છે.",
        "પ્રેમ અને સંબંધો (Heart Matters)": "એકાંતમાં સમય વિતાવવો વધુ ગમશે. જીવનસાથી સાથે કોઈ ગહન વિષય પર ચર્ચા થશે. જૂના સબંધો યાદ આવી શકે.",
        "સ્વાસ્થ્ય અને ફિટનેસ (Body & Soul)": "આંખોમાં થાક કે અનિદ્રાની સમસ્યા થઈ શકે છે. મેડિટેશન કરવાથી માનસિક રાહત મળશે.",
        "દૈનિક ઉપાય (The Spiritual Hack)": "ગરીબોને પીળા રંગનું ભોજન દાન કરો.",
        "પ્રો-ટીપ (Pro-Tip)": "આજે વધુ પડતા વિચારો કરવાને બદલે વર્તમાનમાં જીવવાનો પ્રયત્ન કરો."
      }
    },
    {
      "TITLE": "સિંહ રાશિ - 'The Social King' - 07/05/2026",
      "IMAGE": "singh.jpg",
      "OUTPUT_FILENAME": "singh-rashifal-07052026.mp4",
      "YOUTUBE_SHORT_TITLE": "સિંહ રાશિ: આવકમાં વધારો અને મિત્રોનો સાથ! 💰 #Singh #Success",
      "BG_MUSIC": "Happy & Grand",
      "RASHI_NAME": "SINGH RASHI (સિંહ રાશિ)",
      "content": {
        "આજનો વાઇબ (The Vibe)": "અગિયારમા ભાવમાં ચંદ્ર તમારા માટે લાભના દ્વાર ખોલશે. તમે ખૂબ જ આશાવાદી રહેશો.",
        "કરિયર અને કામકાજ (Work/Hustle)": "વ્યવસાયમાં નવી ભાગીદારીથી મોટો નફો થઈ શકે છે. પ્રોફેશનલ નેટવર્કિંગથી ફાયદો થશે. નોકરીમાં બઢતીના યોગ છે.",
        "પૈસા અને ખિસ્સું (Wallet Talk)": "ધનલાભના પ્રબળ યોગ છે. શેરબજાર કે કમિશનના કામમાં ફાયદો થશે. જૂનું રોકાણ આજે સારું વળતર આપશે.",
        "પ્રેમ અને સંબંધો (Heart Matters)": "મિત્રો સાથેની મુલાકાત યાદગાર રહેશે. સંતાન તરફથી સુખ મળશે. પ્રેમ સંબંધોમાં મધુરતા આવશે.",
        "સ્વાસ્થ્ય અને ફિટનેસ (Body & Soul)": "સ્વાસ્થ્ય એકંદરે સારું રહેશે. માનસિક રીતે તમે ખૂબ જ પોઝિટિવ હશો. બહારનું ખાવાનું ટાળવું.",
        "દૈનિક ઉપાય (The Spiritual Hack)": "કેસરીયા ચંદનનું તિલક કરો અને ઓમ નમો નારાયણાય જાપ કરો.",
        "પ્રો-ટીપ (Pro-Tip)": "આજે તમારી ટીમ અને મિત્રોનો સાથ લેજો, સફળતા સરળ બનશે."
      }
    },
    {
      "TITLE": "કન્યા રાશિ - 'The Ambitious Professional' - 07/05/2026",
      "IMAGE": "kanya.jpg",
      "OUTPUT_FILENAME": "kanya-rashifal-07052026.mp4",
      "YOUTUBE_SHORT_TITLE": "કન્યા રાશિ: કાર્યક્ષેત્રમાં વર્ચસ્વ વધશે, પદ-પ્રતિષ્ઠામાં વધારો! 💼 #Kanya #Career",
      "BG_MUSIC": "Inspiring & Steady",
      "RASHI_NAME": "KANYA RASHI (કન્યા રાશિ)",
      "content": {
        "આજનો વાઇબ (The Vibe)": "દસમા ભાવમાં ચંદ્ર તમારા કરિયરને નવી ઉંચાઈ પર લઈ જશે. તમે આજે ખૂબ જ શિસ્તબદ્ધ અને ગંભીર રહેશો.",
        "કરિયર અને કામકાજ (Work/Hustle)": "બોસ તમારા કામની જાહેરમાં પ્રશંસા કરશે. નવી જવાબદારીઓ મળી શકે છે. રાજકારણ કે સરકારી કામોમાં સફળતા મળશે.",
        "પૈસા અને ખિસ્સું (Wallet Talk)": "આર્થિક સ્થિતિ સ્થિર રહેશે. કરિયરમાં પ્રગતિને કારણે ભવિષ્યમાં ધનલાભ થશે. પ્રોપર્ટીમાં રોકાણ માટે સારો સમય છે.",
        "પ્રેમ અને સંબંધો (Heart Matters)": "પરિવારમાં તમારી વાતનું માન જળવાશે. પિતાના આશીર્વાદ ફળશે. જીવનસાથી સાથે વ્યવસાયિક ચર્ચા થઈ શકે છે.",
        "સ્વાસ્થ્ય અને ફિટનેસ (Body & Soul)": "સ્વાસ્થ્ય સારું રહેશે, પરંતુ કામના બોજને લીધે થાક લાગી શકે છે. રાત્રે હળવું ભોજન લેવું.",
        "દૈનિક ઉપાય (The Spiritual Hack)": "ગુરુ દેવના મંત્ર 'ૐ બૃં બૃહસ્પતયે નમઃ' નો જાપ કરો.",
        "પ્રો-ટીપ (Pro-Tip)": "આજે તમારી મહેનત જ તમારી સાચી ઓળખ બનશે, ફોકસ જાળવી રાખો."
      }
    },
    {
      "TITLE": "તુલા રાશિ - 'The Lucky Explorer' - 07/05/2026",
      "IMAGE": "tula.jpg",
      "OUTPUT_FILENAME": "tula-rashifal-07052026.mp4",
      "YOUTUBE_SHORT_TITLE": "તુલા રાશિ: ભાગ્યનો સાથ મળશે અને ધાર્મિક યાત્રાના યોગ! ✨ #Tula #Luck",
      "BG_MUSIC": "Majestic & Soft",
      "RASHI_NAME": "TULA RASHI (તુલા રાશિ)",
      "content": {
        "આજનો વાઇબ (The Vibe)": "નવમા ભાવમાં ચંદ્ર ભાગ્યને બળ આપશે. આધ્યાત્મિક અને દાર્શનિક વિચારોમાં મન પરોવાયેલું રહેશે.",
        "કરિયર અને કામકાજ (Work/Hustle)": "વિદ્યાર્થીઓ માટે સફળતાનો દિવસ. ઉચ્ચ શિક્ષણના પ્રયત્નો સફળ થશે. લાંબા ગાળાના બિઝનેસ સોદાઓ આજે ફાઈનલ થઈ શકે છે.",
        "પૈસા અને ખિસ્સું (Wallet Talk)": "ધનલાભના યોગ છે. ધાર્મિક પ્રવાસ પાછળ ખર્ચ થઈ શકે છે. નસીબ જોરે અટકેલા નાણાં પાછા મળી શકે છે.",
        "પ્રેમ અને સંબંધો (Heart Matters)": "પરિવારમાં સુખ-શાંતિ રહેશે. વડીલોના સહયોગથી કોઈ મોટું કામ પાર પડશે. જીવનસાથી સાથે તીર્થયાત્રાનું પ્લાનિંગ થઈ શકે.",
        "સ્વાસ્થ્ય અને ફિટનેસ (Body & Soul)": "માનસિક શાંતિ જળવાશે. જૂની બીમારીમાં રાહત મળશે. તાજી હવા અને પ્રાકૃતિક વાતાવરણમાં સમય વિતાવવો.",
        "દૈનિક ઉપાય (The Spiritual Hack)": "શ્રી સૂક્તનો પાઠ કરો અને મંદિરે પીળી મીઠાઈ ચઢાવો.",
        "પ્રો-ટીપ (Pro-Tip)": "આજે ભાગ્ય તમારા પક્ષમાં છે, આત્મવિશ્વાસ સાથે આગળ વધો."
      }
    },
    {
      "TITLE": "વૃશ્ચિક રાશિ - 'The Cautious Strategist' - 07/05/2026",
      "IMAGE": "vrushchik.jpg",
      "OUTPUT_FILENAME": "vrushchik-rashifal-07052026.mp4",
      "YOUTUBE_SHORT_TITLE": "વૃશ્ચિક રાશિ: વાણી પર સંયમ રાખવો અને ઉતાવળ ટાળવી! 🛡️ #Scorpio #Alert",
      "BG_MUSIC": "Steady & Mysterious",
      "RASHI_NAME": "VRUSHCHIK RASHI (વૃશ્ચિક રાશિ)",
      "content": {
        "આજનો વાઇબ (The Vibe)": "આઠમા ભાવમાં ચંદ્ર હોવાથી દિવસ થોડો સાવચેતીભર્યો રહેશે. કોઈ રહસ્યમય બાબત જાણી શકો છો.",
        "કરિયર અને કામકાજ (Work/Hustle)": "કામમાં અવરોધો આવી શકે છે, ધીરજ રાખવી. ગુપ્ત શત્રુઓથી સાવધ રહેવું. કોઈપણ કાગળ પર સહી કરતા પહેલા બરાબર તપાસવું.",
        "પૈસા અને ખિસ્સું (Wallet Talk)": "આર્થિક લેવડદેવડમાં જોખમ ન લેવું. અણધાર્યા ખર્ચ આવી શકે છે. વીમા કે ટેક્સના કામો આજે પૂરા કરવા.",
        "પ્રેમ અને સંબંધો (Heart Matters)": "જીવનસાથી સાથે મતભેદ ટાળવા. સાસરી પક્ષ સાથે સંબંધોમાં ઉતાર-ચઢાવ આવી શકે છે. મૌન ધારણ કરવું શ્રેષ્ઠ છે.",
        "સ્વાસ્થ્ય અને ફિટનેસ (Body & Soul)": "વાહન ચલાવતી વખતે ધ્યાન રાખવું. પેટને લગતી તકલીફ થઈ શકે છે. હળવો ખોરાક લેવો હિતાવહ છે.",
        "દૈનિક ઉપાય (The Spiritual Hack)": "હનુમાન ચાલીસાના પાઠ કરો.",
        "પ્રો-ટીપ (Pro-Tip)": "આજે કોઈના વિવાદમાં ન પડતા, તમારી પોતાની શાંતિ પર ધ્યાન આપો."
      }
    },
    {
      "TITLE": "ધન રાશિ - 'The Dynamic Partner' - 07/05/2026",
      "IMAGE": "dhanu.jpg",
      "OUTPUT_FILENAME": "dhanu-rashifal-07052026.mp4",
      "YOUTUBE_SHORT_TITLE": "ધન રાશિ: વેપારમાં લાભ અને રોમેન્ટિક પળોની સાંજ! ❤️ #Dhanu #Success",
      "BG_MUSIC": "Romantic & Uplifting",
      "RASHI_NAME": "DHANU RASHI (ધન રાશિ)",
      "content": {
        "આજનો વાઇબ (The Vibe)": "સાતમા ભાવમાં ચંદ્ર હોવાથી સંબંધોમાં નવી ઉર્જા આવશે. તમે લોકો સાથે તાલમેલ જાળવવામાં સફળ રહેશો.",
        "કરિયર અને કામકાજ (Work/Hustle)": "ભાગીદારીના વ્યવસાયમાં મોટો નફો થઈ શકે છે. જાહેર જીવનમાં તમારી લોકપ્રિયતા વધશે. નવી ડીલ મળવાની પ્રબળ શક્યતા.",
        "પૈસા અને ખિસ્સું (Wallet Talk)": "આર્થિક સ્થિતિ મજબૂત બનશે. જીવનસાથીના સહયોગથી ધનલાભ થઈ શકે છે. મોજ-શોખ પાછળ ખર્ચ થશે.",
        "પ્રેમ અને સંબંધો (Heart Matters)": "દાંપત્ય જીવનમાં સુખ વધશે. સિંગલ્સને કોઈ યોગ્ય પાત્ર મળી શકે છે. સામાજિક મેળાવડામાં જવાનો અવસર મળશે.",
        "સ્વાસ્થ્ય અને ફિટનેસ (Body & Soul)": "સ્વાસ્થ્ય સારું રહેશે. તમે તાજગી અને સ્ફૂર્તિ અનુભવશો. સાંજનું ભોજન હળવું રાખવું.",
        "દૈનિક ઉપાય (The Spiritual Hack)": "ભગવાન વિષ્ણુને તુલસીના પાન અર્પણ કરો.",
        "પ્રો-ટીપ (Pro-Tip)": "આજે બીજાના મંતવ્યોને પણ માન આપજો, તમને ચોક્કસ ફાયદો થશે."
      }
    },
    {
      "TITLE": "મકર રાશિ - 'The Resilient Worker' - 07/05/2026",
      "IMAGE": "makar.jpg",
      "OUTPUT_FILENAME": "makar-rashifal-07052026.mp4",
      "YOUTUBE_SHORT_TITLE": "મકર રાશિ: વિરોધીઓ હારશે અને કાર્યમાં સફળતા મળશે! 💪 #Makar #Victory",
      "BG_MUSIC": "Bold & Rhythmic",
      "RASHI_NAME": "MAKAR RASHI (મકર રાશિ)",
      "content": {
        "આજનો વાઇબ (The Vibe)": "છઠ્ઠા ભાવમાં ચંદ્ર તમને શક્તિશાળી બનાવશે. પડકારોનો સામનો કરવા તમે માનસિક રીતે તૈયાર રહેશો.",
        "કરિયર અને કામકાજ (Work/Hustle)": "ઓફિસમાં તમારા વિરોધીઓ શાંત રહેશે. કોર્ટ-કચેરીના કામમાં સફળતા મળશે. અટકેલા સરકારી કામોમાં વેગ આવશે.",
        "પૈસા અને ખિસ્સું (Wallet Talk)": "ખર્ચ પર કાબૂ રાખવામાં સફળ રહેશો. જૂના દેવામાંથી મુક્તિ મેળવવાની તક મળશે. બેંકિંગ વ્યવહારમાં સફળતા.",
        "પ્રેમ અને સંબંધો (Heart Matters)": "પરિવારમાં શાંતિ જળવાશે. મોસાળ પક્ષ તરફથી સારા સમાચાર મળી શકે છે. જીવનસાથી સાથે વ્યવહારુ વાતો થશે.",
        "સ્વાસ્થ્ય અને ફિટનેસ (Body & Soul)": "જૂની બીમારીમાં રાહત મળશે. ઇમ્યુનિટી વધારવા પર ધ્યાન આપવું. નિયમિત કસરત કરવી ફાયદાકારક રહેશે.",
        "દૈનિક ઉપાય (The Spiritual Hack)": "પીળા કપડામાં ચણાની દાળ બાંધીને દાન કરો.",
        "પ્રો-ટીપ (Pro-Tip)": "આજે શિસ્તબદ્ધ રીતે કામ કરજો, સફળતા નિશ્ચિત છે."
      }
    },
    {
      "TITLE": "કુંભ રાશિ - 'The Creative Soul' - 07/05/2026",
      "IMAGE": "kumbh.jpg",
      "OUTPUT_FILENAME": "kumbh-rashifal-07052026.mp4",
      "YOUTUBE_SHORT_TITLE": "કુંભ રાશિ: સંતાન સુખ અને બુદ્ધિ ચાતુર્યથી લાભ! 🎨 #Kumbh #Creativity",
      "BG_MUSIC": "Joyful & Light",
      "RASHI_NAME": "KUMBH RASHI (કુંભ રાશિ)",
      "content": {
        "આજનો વાઇબ (The Vibe)": "પાંચમા ભાવમાં ચંદ્ર હોવાથી તમારી ક્રિએટિવિટી ખીલી ઉઠશે. મન પ્રફુલ્લિત રહેશે અને નવા વિચારો આવશે.",
        "કરિયર અને કામકાજ (Work/Hustle)": "શિક્ષણ અને કળા ક્ષેત્રે જોડાયેલા લોકો માટે પ્રગતિનો દિવસ. વિદ્યાર્થીઓને અભ્યાસમાં રુચિ વધશે. રોકાણ માટે દિવસ સારો છે.",
        "પૈસા અને ખિસ્સું (Wallet Talk)": "આર્થિક સ્થિતિ સારી રહેશે. શેરબજાર કે લોટરીથી લાભ થઈ શકે છે. મનોરંજન પાછળ ખર્ચ થશે.",
        "પ્રેમ અને સંબંધો (Heart Matters)": "પ્રેમ સંબંધોમાં રોમાંસ વધશે. સંતાન તરફથી ખુશીના સમાચાર મળશે. મિત્રો સાથે મનગમતી મુલાકાત થશે.",
        "સ્વાસ્થ્ય અને ફિટનેસ (Body & Soul)": "સ્વાસ્થ્ય સારું રહેશે. માનસિક રીતે હળવાશ અનુભવશો. મનગમતી પ્રવૃત્તિમાં સમય વિતાવવો.",
        "દૈનિક ઉપાય (The Spiritual Hack)": "ગુરુ ચાલીસાનો પાઠ કરો.",
        "પ્રો-ટીપ (Pro-Tip)": "આજે તમારા શોખને સમય આપજો, તેનાથી નવી ઉર્જા મળશે."
      }
    },
    {
      "TITLE": "મીન રાશિ - 'The Peaceful Homebody' - 07/05/2026",
      "IMAGE": "meen.jpg",
      "OUTPUT_FILENAME": "meen-rashifal-07052026.mp4",
      "YOUTUBE_SHORT_TITLE": "મીન રાશિ: ઘરમાં સુખ-શાંતિ અને નવી પ્રોપર્ટીના યોગ! 🏡 #Meen #Home",
      "BG_MUSIC": "Soothing & Calm",
      "RASHI_NAME": "MEEN RASHI (મીન રાશિ)",
      "content": {
        "આજનો વાઇબ (The Vibe)": "ચોથા ભાવમાં ચંદ્ર હોવાથી મન ઘરેલું સુખ અને શાંતિમાં પરોવાયેલું રહેશે. માનસિક સંતોષ મળશે.",
        "કરિયર અને કામકાજ (Work/Hustle)": "વર્ક ફ્રોમ હોમ કરતા લોકોને સફળતા મળશે. જમીન કે વાહન ખરીદવાનું વિચારી રહ્યા હોવ તો પ્રગતિ થશે. ઓફિસમાં વાતાવરણ શાંત રહેશે.",
        "પૈસા અને ખિસ્સું (Wallet Talk)": "ઘરેલું સુખ-સુવિધા પાછળ ખર્ચ થશે. માતા તરફથી ધનલાભ થઈ શકે છે. આર્થિક રીતે તમે સુરક્ષિત અનુભવશો.",
        "પ્રેમ અને સંબંધો (Heart Matters)": "માતા સાથેના સંબંધો મધુર બનશે. જીવનસાથી સાથે ઘરની વ્યવસ્થા અંગે ચર્ચા થશે. ઘરમાં પ્રસન્નતાનું વાતાવરણ રહેશે.",
        "સ્વાસ્થ્ય અને ફિટનેસ (Body & Soul)": "સ્વાસ્થ્ય સારું રહેશે, પરંતુ માનસિક સંવેદનશીલતા વધી શકે છે. પ્રાણાયામ અને પૂરતી ઊંઘ લેવી.",
        "દૈનિક ઉપાય (The Spiritual Hack)": "શિવલિંગ પર દૂધ અને મધ અર્પણ કરો.",
        "પ્રો-ટીપ (Pro-Tip)": "આજે બહારની દોડધામ કરતા પરિવાર સાથેની શાંતિ વધુ સારી લાગશે."
      }
    }
  ]
}
